Metadata-Version: 2.1
Name: shirker
Version: 1.0.0
Summary: run command and send stdout+stderr to slack
Home-page: http://github.com/drorspei/shirker
Author: Dror Speiser
License: MIT
License-File: LICENSE
